README
csmash.py
setup.py
configsmash.egg-info/PKG-INFO
configsmash.egg-info/SOURCES.txt
configsmash.egg-info/dependency_links.txt
configsmash.egg-info/entry_points.txt
configsmash.egg-info/requires.txt
configsmash.egg-info/top_level.txt