Metadata-Version: 1.0
Name: configsmash
Version: 0.0.2
Summary: python lib / script for reading cascading sets of ini files
Home-page: https://github.com/rranshous/configsmash
Author: Robby Ranshous
Author-email: rranshous@gmail.com
License: UNKNOWN
Keywords: configuration
Platform: UNKNOWN
Classifier: Development Status :: 3 - Alpha
Classifier: Topic :: Utilities
Classifier: Programming Language :: Python :: 2.6
Classifier: Programming Language :: Python :: 2.7
Classifier: Programming Language :: Python :: 3.2
